[
  {
    "_class": "pl.hackyeah2019.hackyeah.product.PackageMaterial",
    "id": 1,
    "code": "PP05",
    "logo": "http://www.plasticexpert.co.uk/wp-content/uploads/2014/07/images.jpg",
    "recyclePotential": 30,
    "timeToBiodegradateInDays": 365
  },
  {
    "_class": "pl.hackyeah2019.hackyeah.product.PackageMaterial",
    "id": 2,
    "code": "Paper",
    "logo": "https://cdn3.vectorstock.com/i/1000x1000/76/07/conceptual-recycling-paper-recycle-sign-icon-vector-17677607.jpg",
    "recyclePotential": 100,
    "timeToBiodegradateInDays": 14
  },
  {
    "_class": "pl.hackyeah2019.hackyeah.product.PackageMaterial",
    "id": 3,
    "code": "Glass",
    "logo": "https://d1yjjnpx0p53s8.cloudfront.net/styles/logo-thumbnail/s3/0003/4707/brand.gif?itok=gAnPFe3Q",
    "recyclePotential": 100,
    "timeToBiodegradateInDays": 365000000
  },
  {
    "_class": "pl.hackyeah2019.hackyeah.product.PackageMaterial",
    "id": 4,
    "code": "PE-LD",
    "logo": "https://daloplast.se/wp-content/uploads/2015/12/LDPE_04.png",
    "recyclePotential": 60,
    "timeToBiodegradateInDays": 365000
  },
  {
    "_class": "pl.hackyeah2019.hackyeah.product.PackageMaterial",
    "id": 5,
    "code": "7 Other",
    "logo": "https://image.shutterstock.com/image-photo/image-260nw-1459165832.jpg",
    "recyclePotential": 20,
    "timeToBiodegradateInDays": 91
  }
]



